{
  "components": [
    {
      "data": {
        "contents_checksum": "cbe989aff03e61af3e43395fa240ddc702451d928eb10a2ccffa713b27180d12",
        "source": "",
        "type": "tar"
      },
      "dependencies": [
        "core",
        "gcloud-deps-darwin-x86",
        "gcloud-deps-darwin-x86_64",
        "gcloud-deps-linux-x86",
        "gcloud-deps-linux-x86_64",
        "gcloud-deps-windows-x86",
        "gcloud-deps-windows-x86_64"
      ],
      "details": {
        "description": "Set of third_party gcloud cli dependencies.",
        "display_name": "gcloud cli dependencies"
      },
      "id": "gcloud-deps",
      "is_configuration": false,
      "is_hidden": true,
      "is_required": false,
      "platform": {},
      "platform_required": false,
      "version": {
        "build_number": 20240712142834,
        "version_string": "2024.07.12"
      }
    }
  ],
  "revision": 20240712142834,
  "schema_version": {
    "no_update": false,
    "url": "https://dl.google.com/dl/cloudsdk/channels/rapid/google-cloud-sdk.tar.gz",
    "version": 3
  },
  "version": "484.0.0"
}